donb_config/__init__.py
donb_config/base_class.py
donb_config/interface_repo_config.py
donb_config/manager.py
donb_config/py.typed
donb_config/types.py
donb_config/ruamel_yaml/__init__.py
donb_config/ruamel_yaml/repo_config_yaml.py
donb_config-1.3.0.dist-info/METADATA
donb_config-1.3.0.dist-info/WHEEL
donb_config-1.3.0.dist-info/top_level.txt
donb_config-1.3.0.dist-info/RECORD
